census/__init__.py
census/admin.py
census/context_processors.py
census/models.py
census/profile.py
census/tests.py
census/topics.py
census/urls.py
census/utils.py
census/views.py
census/fixtures/summary_levels.json
census/management/__init__.py
census/management/commands/__init__.py
census/management/commands/cache_to_s3.py
census/management/commands/taxonify_table_metadata.py
census/migrations/0001_initial.py
census/migrations/0002_python3_port_20190315_0944.py
census/migrations/__init__.py
census/static/embed.html
census/static/iframe.html
census/static/tilelayer.html
census/static/css/_empty.scss
census/static/css/vendor/Grid.css
census/static/css/vendor/leaflet-0.6.4.css
census/static/css/vendor/leaflet-0.6.4.ie.css
census/static/css/vendor/leaflet.label.css
census/static/css/vendor/normalize.css
census/static/css/vendor/normalize.min.css
census/static/css/vendor/images/layers-2x.png
census/static/css/vendor/images/layers.png
census/static/css/vendor/images/marker-icon-2x.png
census/static/css/vendor/images/marker-icon.png
census/static/css/vendor/images/marker-shadow.png
census/static/css/vendor/select2/select2.css
census/static/css/vendor/select2/select2.png
census/static/css/vendor/select2/select2.textinput.css
census/static/css/vendor/select2/select2x2.png
census/static/css/vendor/select2/spinner.gif
census/static/img/code4sa-logo-small.png
census/static/img/logo-48x24.png
census/static/img/logo-embed.png
census/static/img/logo.png
census/static/img/logo12.png
census/static/img/mma.png
census/static/img/openup-logo-small.png
census/static/img/wazi-logo.png
census/static/img/examples/education_cleveland.png
census/static/img/examples/hover_over_graph.png
census/static/img/examples/language_los_angeles.png
census/static/img/examples/map_search.png
census/static/img/examples/poverty_spokane.png
census/static/img/examples/section_overview.png
census/static/img/examples/text_search.png
census/static/img/examples/us_geographic_mobility_distribution.png
wazimap-2.1.0.dist-info/LICENSE
wazimap-2.1.0.dist-info/METADATA
wazimap-2.1.0.dist-info/WHEEL
wazimap-2.1.0.dist-info/top_level.txt
wazimap-2.1.0.dist-info/RECORD
