Metadata-Version: 2.1
Name: wazimap
Version: 2.1.0
Summary: A Django application for exploring census and other place-specific data
Home-page: https://github.com/OpenUpSA/wazimap
Author: OpenUp
Author-email: webapps@openup.org.za
License: MIT
Platform: UNKNOWN
Classifier: Development Status :: 4 - Beta
Classifier: Intended Audience :: Developers
Classifier: License :: OSI Approved :: MIT License
Classifier: Programming Language :: Python
Classifier: Programming Language :: Python :: 3
Classifier: Programming Language :: Python :: 3.6
Requires-Dist: Django (==2.2.6)
Requires-Dist: SQLAlchemy (>=1.2.17)
Requires-Dist: boto (>=2.49.0)
Requires-Dist: dj-database-url (>=0.5.0)
Requires-Dist: django-compressor (>=2.2)
Requires-Dist: django-cors-headers (>=3.1.0)
Requires-Dist: django-pipeline (>=1.6.14)
Requires-Dist: django-sass-processor (>=0.7.3)
Requires-Dist: ecdsa (>=0.11)
Requires-Dist: libsass (>=0.17.0)
Requires-Dist: paramiko (<2,>=1.18.5)
Requires-Dist: psycopg2 (>=2.7.7)
Requires-Dist: requests (>=2.21)
Requires-Dist: unicodecsv (>=0.14.1)
Requires-Dist: whitenoise (>=4.1.2)
Provides-Extra: dev
Requires-Dist: flake8 ; extra == 'dev'
Requires-Dist: nose ; extra == 'dev'
Provides-Extra: gdal
Requires-Dist: GDAL ; extra == 'gdal'
Requires-Dist: Shapely (>=1.5.13) ; extra == 'gdal'
Provides-Extra: test
Requires-Dist: flake8 ; extra == 'test'
Requires-Dist: nose ; extra == 'test'
